fortcookie/__init__.py
fortcookie/cookie.py
fortcookie-0.0.3.dist-info/LICENSE
fortcookie-0.0.3.dist-info/METADATA
fortcookie-0.0.3.dist-info/WHEEL
fortcookie-0.0.3.dist-info/top_level.txt
fortcookie-0.0.3.dist-info/RECORD
