Metadata-Version: 2.1
Name: fortcookie
Version: 0.0.3
Summary: Say cookie.crack() and be lucky...
Home-page: https://github.com/rafaelstojoao/fortcookie
Author: Rafael Stoffalette Joao
Author-email: rafaelstojoao@gmail.com
License: UNKNOWN
Platform: UNKNOWN
Classifier: Programming Language :: Python :: 3
Classifier: License :: OSI Approved :: MIT License
Classifier: Operating System :: OS Independent
Requires-Python: >=3.6
